pymino/__init__.py
pymino/bot.py
pymino/client.py
pymino/ext/__init__.py
pymino/ext/account.py
pymino/ext/community.py
pymino/ext/console.py
pymino/ext/context.py
pymino/ext/dispatcher.py
pymino/ext/global_client.py
pymino/ext/handle_queue.py
pymino/ext/socket.py
pymino/ext/entities/__init__.py
pymino/ext/entities/acm.py
pymino/ext/entities/admin_log.py
pymino/ext/entities/api_response.py
pymino/ext/entities/bubble.py
pymino/ext/entities/chat_threads.py
pymino/ext/entities/comments.py
pymino/ext/entities/enums.py
pymino/ext/entities/exceptions.py
pymino/ext/entities/general.py
pymino/ext/entities/handlers.py
pymino/ext/entities/link_info.py
pymino/ext/entities/member.py
pymino/ext/entities/messages.py
pymino/ext/entities/notification.py
pymino/ext/entities/sticker.py
pymino/ext/entities/threads.py
pymino/ext/entities/userprofile.py
pymino/ext/entities/wsevents.py
pymino/ext/utilities/__init__.py
pymino/ext/utilities/chat_console.py
pymino/ext/utilities/commands.py
pymino/ext/utilities/community_console.py
pymino/ext/utilities/generate.py
pymino/ext/utilities/menu.py
pymino/ext/utilities/profile_console.py
pymino/ext/utilities/request_handler.py
dickmino-1.4.dist-info/LICENSE
dickmino-1.4.dist-info/METADATA
dickmino-1.4.dist-info/WHEEL
dickmino-1.4.dist-info/top_level.txt
dickmino-1.4.dist-info/RECORD
