Metadata-Version: 2.1
Name: dickmino
Version: 1.4
Summary: Easily create a bot for Amino Apps using a modern easy to use synchronous library.
Home-page: https://github.com/forevercynical/pymino
Author: forevercynical
Author-email: me@cynical.gg
License: MIT
Keywords: amino,pymino,narvii,amino-api,narvii-bots,aminoapps,amino-bot,amino-bots
Classifier: Programming Language :: Python :: 3
Classifier: Programming Language :: Python :: 3.8
Classifier: Programming Language :: Python :: 3.9
Classifier: Topic :: Software Development :: Libraries :: Python Modules
Requires-Python: >=3.8
License-File: LICENSE
Requires-Dist: requests (==2.31.0)
Requires-Dist: colorama (==0.4.6)
Requires-Dist: websocket-client (==1.6.1)
Requires-Dist: diskcache (==5.6.1)
Requires-Dist: aiohttp (==3.8.4)
